mrflagly-0.2.14.dist-info/METADATA
mrflagly-0.2.14.dist-info/WHEEL
mrflagly/__init__.py
mrflagly/mrflagly.abi3.so
mrflagly-0.2.14.dist-info/RECORD
