Metadata-Version: 2.4
Name: mrflagly
Version: 0.2.14
Classifier: Programming Language :: Rust
Classifier: Programming Language :: Python :: Implementation :: CPython
Classifier: Programming Language :: Python :: Implementation :: PyPy
Summary: No nonsense feature flagging system
Home-Page: https://github.com/vangheem/mr.flagly
Author-email: Nathan Van Gheem <vangheem@gmail.com>>
Requires-Python: >=3.10
